science_data_structure/__init__.py
science_data_structure/author.py
science_data_structure/config.py
science_data_structure/core.py
science_data_structure/data_formats.py
science_data_structure/descriptions.py
science_data_structure/logger.py
science_data_structure/meta.py
science_data_structure/permissions.py
science_data_structure/structures.py
science_data_structure/test_author.py
science_data_structure/test_config.py
science_data_structure/test_logger.py
science_data_structure/test_meta.py
science_data_structure/test_structures.py
science_data_structure/data_formats/__init__.py
science_data_structure/data_formats/general_formats.py
science_data_structure/parsers/__init__.py
science_data_structure/parsers/matlab_parser.py
science_data_structure/tools/__init__.py
science_data_structure/tools/files.py
science_data_structure/tools/manage.py
science_data_structure/tools/test_files.py
science_data_structure/tools/test_manage.py
scripts/__init__.py
scripts/yourscript.py
science_data_structure-0.0.4.dist-info/LICENSE
science_data_structure-0.0.4.dist-info/METADATA
science_data_structure-0.0.4.dist-info/WHEEL
science_data_structure-0.0.4.dist-info/entry_points.txt
science_data_structure-0.0.4.dist-info/top_level.txt
science_data_structure-0.0.4.dist-info/RECORD
