Metadata-Version: 2.1
Name: science-data-structure
Version: 0.0.4
Summary: Structure for large data-sets in science
Home-page: https://github.com/woutervanveen/science_data_structure
Author: Wouter van Veen
License: UNKNOWN
Platform: UNKNOWN
Classifier: Programming Language :: Python :: 3
Classifier: License :: OSI Approved :: MIT License
Classifier: Operating System :: OS Independent
Requires-Python: >=3.8
Requires-Dist: Click
